pytorch_cosma/__init__.py
pytorch_cosma/autoencoders.py
pytorch_cosma/basic_layers.py
pytorch_cosma/config_validation.py
pytorch_cosma/graph_exploration.py
pytorch_cosma/latent_space.py
pytorch_cosma/model_yaml_parser.py
pytorch_cosma/network_construction.py
pytorch_cosma/utils.py
pytorch_cosma/vision_transformer.py
pytorch_cosma-0.1.27.dist-info/METADATA
pytorch_cosma-0.1.27.dist-info/WHEEL
pytorch_cosma-0.1.27.dist-info/top_level.txt
pytorch_cosma-0.1.27.dist-info/RECORD
