Metadata-Version: 2.2
Name: pytorch-cosma
Version: 0.1.27
Summary: A deep learning framework built on top of PyTorch.
Author-email: Ra'ad Costello-Mahmoud <mahmoud.raad@yahoo.co.uk>
License: MIT
Project-URL: homepage, https://github.com/raadcostellomahmoud/pytorch-cosma
Project-URL: repository, https://github.com/raadcostellomahmoud/pytorch-cosma
Classifier: Programming Language :: Python :: 3
Classifier: License :: OSI Approved :: MIT License
Classifier: Operating System :: OS Independent
Requires-Python: >=3.10
Requires-Dist: aiohttp
Requires-Dist: dash
Requires-Dist: Flask
Requires-Dist: matplotlib
Requires-Dist: networkx
Requires-Dist: nvidia-cublas-cu12
Requires-Dist: nvidia-cuda-cupti-cu12
Requires-Dist: nvidia-cuda-nvrtc-cu12
Requires-Dist: nvidia-cuda-runtime-cu12
Requires-Dist: nvidia-cudnn-cu12
Requires-Dist: nvidia-cufft-cu12
Requires-Dist: nvidia-curand-cu12
Requires-Dist: nvidia-cusolver-cu12
Requires-Dist: nvidia-cusparse-cu12
Requires-Dist: nvidia-nccl-cu12
Requires-Dist: nvidia-nvjitlink-cu12
Requires-Dist: nvidia-nvtx-cu12
Requires-Dist: opencv-python
Requires-Dist: packaging
Requires-Dist: pandas
Requires-Dist: pillow
Requires-Dist: psutil
Requires-Dist: pydantic
Requires-Dist: PyYAML
Requires-Dist: requests
Requires-Dist: scikit-learn
Requires-Dist: scikit-learn-intelex
Requires-Dist: scipy
Requires-Dist: torch>=2.5.1
Requires-Dist: torch-geometric>=2.6.1
Requires-Dist: torchaudio>=2.5.1
Requires-Dist: torchvision>=0.20.1
Requires-Dist: tqdm
Requires-Dist: umap-learn
